topsis_3356/code.py
topsis_3356-1.0.1.dist-info/LICENCE.txt
topsis_3356-1.0.1.dist-info/METADATA
topsis_3356-1.0.1.dist-info/WHEEL
topsis_3356-1.0.1.dist-info/entry_points.txt
topsis_3356-1.0.1.dist-info/top_level.txt
topsis_3356-1.0.1.dist-info/RECORD
