Metadata-Version: 2.1
Name: topsis-3356
Version: 1.0.1
Summary: A Python package.
Home-page: https://github.com/muskangupta3356/topsis_3356
Author: MUSKAN GUPTA
Author-email: muskangupta270798@gmail.com
License: MIT
Platform: UNKNOWN
Classifier: License :: OSI Approved :: MIT License
Classifier: Programming Language :: Python :: 3
Classifier: Programming Language :: Python :: 3.7
Requires-Dist: requests
